wtfismyip.py
wtfismyip-1.0.3.dist-info/METADATA
wtfismyip-1.0.3.dist-info/WHEEL
wtfismyip-1.0.3.dist-info/entry_points.txt
wtfismyip-1.0.3.dist-info/top_level.txt
wtfismyip-1.0.3.dist-info/RECORD
