Metadata-Version: 2.4
Name: wtfismyip
Version: 1.0.3
Summary: A simple command line tool to get your public IP address.
Author-email: "Jorge Alberto Díaz Orozco (Akiel)" <diazorozcoj@gmail.com>
License-Expression: MIT
Requires-Dist: requests
Requires-Dist: rich
